<Updates>
 <ApplicationName>{AnyApplication}</ApplicationName>
 <ApplicationVersion>1.0.0</ApplicationVersion>
 <Checksum>true</Checksum>
 <PackageUpdate>
  <Name>com.vlt.product</Name>
  <Script>installscript.qs</Script>
  <DisplayName>The root component</DisplayName>
  <Description>this is the main program</Description>
  <Version>0.1.0-1</Version>
  <ReleaseDate>2010-09-21</ReleaseDate>
  <ForcedInstallation>true</ForcedInstallation>
  <UpdateFile UncompressedSize="5260376" OS="Any" CompressedSize="2116567"/>
  <DownloadableArchives>data.7z</DownloadableArchives>
  <SHA1>5463bf8e693e6f14df5fe097307c9dad5bedc58f</SHA1>
 </PackageUpdate>
 <PackageUpdate>
  <Name>com.vlt.product.a</Name>
  <DisplayName>Part a</DisplayName>
  <Description>this is te first part of the program</Description>
  <Version>0.1.0-1</Version>
  <ReleaseDate>2010-09-21</ReleaseDate>
  <ForcedInstallation>true</ForcedInstallation>
  <UpdateFile UncompressedSize="40000040" OS="Any" CompressedSize="39655823"/>
  <DownloadableArchives>content.7z</DownloadableArchives>
  <SHA1>bb2193ef87b94ed54d5af36171004be7ef7cac1f</SHA1>
 </PackageUpdate>
 <PackageUpdate>
  <Name>com.vlt.product.b</Name>
  <DisplayName>Part B</DisplayName>
  <Description>this is the second part of the java installer</Description>
  <Version>0.1.0-1</Version>
  <ReleaseDate>2010-09-21</ReleaseDate>
  <ForcedInstallation>true</ForcedInstallation>
  <UpdateFile UncompressedSize="39214340" OS="Any" CompressedSize="38752271"/>
  <DownloadableArchives>content.7z</DownloadableArchives>
  <SHA1>f1f29345d2a2a0fd03d980d9226eff262b9603be</SHA1>
 </PackageUpdate>
</Updates>
